hl_mcp_server-0.1.0.dist-info/licenses/LICENSE
hyperliquid_mcp/__init__.py
hyperliquid_mcp/__main__.py
hyperliquid_mcp/server.py
hyperliquid_mcp/version.py
hl_mcp_server-0.1.0.dist-info/METADATA
hl_mcp_server-0.1.0.dist-info/WHEEL
hl_mcp_server-0.1.0.dist-info/entry_points.txt
hl_mcp_server-0.1.0.dist-info/top_level.txt
hl_mcp_server-0.1.0.dist-info/RECORD
